rfctl/__init__.py
rfctl/rfctl.py
rfctl/util.py
rfctl/version.py
rfctl/version.txt
rfctl/dirtools/LICENSE
rfctl/dirtools/README.rst
rfctl/dirtools/__init__.py
rfctl/dirtools/globster.py
rfctl/dirtools/lazy_regex.py
rfctl-1.1.1.dist-info/DESCRIPTION.rst
rfctl-1.1.1.dist-info/METADATA
rfctl-1.1.1.dist-info/RECORD
rfctl-1.1.1.dist-info/WHEEL
rfctl-1.1.1.dist-info/entry_points.txt
rfctl-1.1.1.dist-info/metadata.json
rfctl-1.1.1.dist-info/top_level.txt
